pyterrier_sentence_transformers/__init__.py
pyterrier_sentence_transformers/base.py
pyterrier_sentence_transformers/index.py
pyterrier_sentence_transformers/indexer.py
pyterrier_sentence_transformers/retriever.py
pyterrier_sentence_transformers-0.2.2.dist-info/LICENSE
pyterrier_sentence_transformers-0.2.2.dist-info/METADATA
pyterrier_sentence_transformers-0.2.2.dist-info/WHEEL
pyterrier_sentence_transformers-0.2.2.dist-info/top_level.txt
pyterrier_sentence_transformers-0.2.2.dist-info/RECORD
