Metadata-Version: 2.1
Name: pyterrier-sentence-transformers
Version: 0.2.2
Summary: Create an pyterrier index using any sentence-transformers model
Author-email: Luca Soldaini <luca@soldaini.net>
License: Apache-2.0
Project-URL: Homepage, https://github.com/soldni/pyterrier_sentence_transformers
Requires-Python: >=3.8
License-File: LICENSE
Requires-Dist: pandas
Requires-Dist: tensorboardX
Requires-Dist: python-terrier
Requires-Dist: sentence-transformers (<3.0.0,>=2.2.2)
Requires-Dist: transformers (<5.0.0,>=4.22.1)
Requires-Dist: necessary (>=0.2.3)
Requires-Dist: trouting (>=0.3.0)
Requires-Dist: platformdirs (>=2.5.0)
Provides-Extra: dev
Requires-Dist: black (>=22.6.0) ; extra == 'dev'
Requires-Dist: springs (>=1.4.5) ; extra == 'dev'
Requires-Dist: isort (>=5.10.1) ; extra == 'dev'
Requires-Dist: mypy (>=0.971) ; extra == 'dev'
Requires-Dist: pytest (>=5.2) ; extra == 'dev'
Requires-Dist: ipython (>=8.4.0) ; extra == 'dev'
Requires-Dist: autopep8 (>=1.7.0) ; extra == 'dev'
Requires-Dist: flake8 (>=5.0) ; extra == 'dev'
Requires-Dist: ipdb (>=0.13.0) ; extra == 'dev'
Requires-Dist: flake8-pyi (>=22.8.1) ; extra == 'dev'
Requires-Dist: Flake8-pyproject (>=1.1.0) ; extra == 'dev'
